parse/LATEXdefinitions.py
parse/__init__.py
texconv-0.0.1.dist-info/METADATA
texconv-0.0.1.dist-info/WHEEL
texconv-0.0.1.dist-info/top_level.txt
texconv-0.0.1.dist-info/RECORD
